musiclab/__init__.py
musiclab/score.py
musiclab/vlc_player.cpython-312-darwin.so
musiclab/extras/datamapping.cpython-312-darwin.so
musiclab/fluidmidi/pyside/bytearray.cpython-312-darwin.so
musiclab/fluidmidi/pyside/midi.cpython-312-darwin.so
musiclab/fluidsynth/fsynth.cpython-312-darwin.so
musiclab/fluidsynth/libfluidsynth/Library/Frameworks/FluidSynth.framework/FluidSynth
musiclab/fluidsynth/libfluidsynth/Library/Frameworks/FluidSynth.framework/Contents/Frameworks/libglib-2.0.0.dylib
musiclab/fluidsynth/libfluidsynth/Library/Frameworks/FluidSynth.framework/Contents/Frameworks/libgthread-2.0.0.dylib
musiclab/fluidsynth/libfluidsynth/Library/Frameworks/FluidSynth.framework/Contents/Frameworks/libintl.8.dylib
musiclab/fluidsynth/libfluidsynth/Library/Frameworks/FluidSynth.framework/Contents/Frameworks/libsndfile.1.dylib
musiclab/fluidsynth/libfluidsynth/Library/Frameworks/FluidSynth.framework/Versions/3/FluidSynth
musiclab/fluidsynth/libfluidsynth/Library/Frameworks/FluidSynth.framework/Versions/3/Headers/fluidsynth.h
musiclab/fluidsynth/libfluidsynth/Library/Frameworks/FluidSynth.framework/Versions/3/Headers/fluidsynth/audio.h
musiclab/fluidsynth/libfluidsynth/Library/Frameworks/FluidSynth.framework/Versions/3/Headers/fluidsynth/event.h
musiclab/fluidsynth/libfluidsynth/Library/Frameworks/FluidSynth.framework/Versions/3/Headers/fluidsynth/gen.h
musiclab/fluidsynth/libfluidsynth/Library/Frameworks/FluidSynth.framework/Versions/3/Headers/fluidsynth/ladspa.h
musiclab/fluidsynth/libfluidsynth/Library/Frameworks/FluidSynth.framework/Versions/3/Headers/fluidsynth/log.h
musiclab/fluidsynth/libfluidsynth/Library/Frameworks/FluidSynth.framework/Versions/3/Headers/fluidsynth/midi.h
musiclab/fluidsynth/libfluidsynth/Library/Frameworks/FluidSynth.framework/Versions/3/Headers/fluidsynth/misc.h
musiclab/fluidsynth/libfluidsynth/Library/Frameworks/FluidSynth.framework/Versions/3/Headers/fluidsynth/mod.h
musiclab-0.38.0.dist-info/METADATA
musiclab-0.38.0.dist-info/WHEEL
musiclab-0.38.0.dist-info/entry_points.txt
musiclab-0.38.0.dist-info/top_level.txt
musiclab-0.38.0.dist-info/RECORD
